Industrial_time_series_analysis/__init__.py
Industrial_time_series_analysis/Control/PMCCL.py
Industrial_time_series_analysis/Control/__init__.py
Industrial_time_series_analysis/Control/contron_utils/__init__.py
Industrial_time_series_analysis/Control/contron_utils/pmccl_util/__init__.py
Industrial_time_series_analysis/Control/contron_utils/pmccl_util/evaluate.py
Industrial_time_series_analysis/Control/contron_utils/pmccl_util/test.py
Industrial_time_series_analysis/Control/contron_utils/pmccl_util/train.py
Industrial_time_series_analysis/Control/contron_utils/pmccl_util/datasets/TimeDataset.py
Industrial_time_series_analysis/Control/contron_utils/pmccl_util/datasets/__init__.py
Industrial_time_series_analysis/Control/contron_utils/pmccl_util/models/CNN.py
Industrial_time_series_analysis/Control/contron_utils/pmccl_util/models/GDN.py
Industrial_time_series_analysis/Control/contron_utils/pmccl_util/models/GRU.py
Industrial_time_series_analysis/Control/contron_utils/pmccl_util/models/LSTM.py
Industrial_time_series_analysis/Control/contron_utils/pmccl_util/models/LSTMVAE.py
Industrial_time_series_analysis/Control/contron_utils/pmccl_util/models/MLP.py
Industrial_time_series_analysis/Control/contron_utils/pmccl_util/models/RNN.py
Industrial_time_series_analysis/Control/contron_utils/pmccl_util/models/Transformer.py
Industrial_time_series_analysis/Control/contron_utils/pmccl_util/models/__init__.py
Industrial_time_series_analysis/Control/contron_utils/pmccl_util/util/__init__.py
Industrial_time_series_analysis/Control/contron_utils/pmccl_util/util/data.py
Industrial_time_series_analysis/Control/contron_utils/pmccl_util/util/env.py
Industrial_time_series_analysis/Control/contron_utils/pmccl_util/util/ewc_utils.py
Industrial_time_series_analysis/Control/contron_utils/pmccl_util/util/iostream.py
Industrial_time_series_analysis/Control/contron_utils/pmccl_util/util/loss_func.py
Industrial_time_series_analysis/Control/contron_utils/pmccl_util/util/net_struct.py
Industrial_time_series_analysis-2.2.3.dist-info/METADATA
Industrial_time_series_analysis-2.2.3.dist-info/WHEEL
Industrial_time_series_analysis-2.2.3.dist-info/top_level.txt
Industrial_time_series_analysis-2.2.3.dist-info/RECORD
