Metadata-Version: 2.1
Name: Industrial_time_series_analysis
Version: 2.2.3
Summary: A time series data analysis algorithm library for industrial scenarios
Author: PYJ
Author-email: 3463146475@qq.com
Project-URL: Source, https://github.com/PANYJIE/Industrial_time_series_analysis
Requires-Python: >=3.6
